ovos_local_backend/__init__.py
ovos_local_backend/__main__.py
ovos_local_backend/configuration.py
ovos_local_backend/session.py
ovos_local_backend/version.py
ovos_local_backend/backend/__init__.py
ovos_local_backend/backend/admin.py
ovos_local_backend/backend/auth.py
ovos_local_backend/backend/decorators.py
ovos_local_backend/backend/device.py
ovos_local_backend/backend/external_apis.py
ovos_local_backend/backend/precise.py
ovos_local_backend/backend/stt.py
ovos_local_backend/database/__init__.py
ovos_local_backend/database/metrics.py
ovos_local_backend/database/oauth.py
ovos_local_backend/database/settings.py
ovos_local_backend/database/utterances.py
ovos_local_backend/database/wakewords.py
ovos_local_backend/utils/__init__.py
ovos_local_backend/utils/geolocate.py
ovos_local_backend/utils/mail.py
ovos_local_backend/utils/selene.py
ovos_local_backend-0.1.5.dist-info/LICENSE
ovos_local_backend-0.1.5.dist-info/METADATA
ovos_local_backend-0.1.5.dist-info/WHEEL
ovos_local_backend-0.1.5.dist-info/entry_points.txt
ovos_local_backend-0.1.5.dist-info/top_level.txt
ovos_local_backend-0.1.5.dist-info/RECORD
