Metadata-Version: 2.1
Name: ovos-local-backend
Version: 0.1.5
Summary: mock mycroft backend
Home-page: https://github.com/OpenVoiceOS/OVOS-local-backend
Author: jarbasAI
Author-email: jarbasai@mailfence.com
License: Apache-2.0
Platform: UNKNOWN
Requires-Dist: Flask (>=0.12)
Requires-Dist: json-database (~=0.7)
Requires-Dist: requests (>=2.26.0)
Requires-Dist: pyOpenSSL
Requires-Dist: ovos-utils (>=0.0.25a7)
Requires-Dist: ovos-plugin-manager
Requires-Dist: ovos-stt-plugin-server
Requires-Dist: geocoder
Requires-Dist: timezonefinder
Requires-Dist: requests-cache
Requires-Dist: ovos-backend-client (>=0.0.5a3,~=0.0)
Requires-Dist: oauthlib (~=3.0)
